MANIFEST.in
README.md
setup.cfg
setup.py
courses/.DS_Store
courses/__init__.py
courses/import_course_path.py
courses/Data_Analysis/.DS_Store
courses/Data_Analysis/__init__.py
courses/Data_Analysis/course.yaml
courses/Data_Analysis/initialize_lesson.py
courses/Data_Analysis/__pycache__/__init__.cpython-37.pyc
courses/Data_Analysis/__pycache__/initialize_lesson.cpython-37.pyc
courses/Data_Analysis/lessons/.DS_Store
courses/Data_Analysis/lessons/Explore-Data.yaml
courses/Demo_Course/.DS_Store
courses/Demo_Course/course.yaml
courses/Demo_Course/initialize_lesson.py
courses/Demo_Course/__pycache__/initialize_lesson.cpython-37.pyc
courses/Demo_Course/lessons/.DS_Store
courses/Demo_Course/lessons/demo-lesson-one.yaml
courses/Demo_Course/lessons/demo-lesson-two.yaml
courses/Demo_Course/scripts/.DS_Store
courses/Demo_Course/scripts/__init__.py
courses/Demo_Course/scripts/boring_function.py
courses/Demo_Course/scripts/boring_function_correct.py
courses/Demo_Course/scripts/custom_tests.py
courses/Demo_Course/scripts/__pycache__/__init__.cpython-37.pyc
courses/Demo_Course/scripts/__pycache__/boring_function.cpython-37.pyc
courses/Demo_Course/scripts/__pycache__/boring_function_correct.cpython-37.pyc
courses/Python_Programming/.DS_Store
courses/Python_Programming/__init__.py
courses/Python_Programming/course.yaml
courses/Python_Programming/custom_tests.py
courses/Python_Programming/initialize_lesson.py
courses/Python_Programming/__pycache__/__init__.cpython-37.pyc
courses/Python_Programming/__pycache__/initialize_lesson.cpython-37.pyc
courses/Python_Programming/lessons/.DS_Store
courses/Python_Programming/lessons/Lists-In-Python.yaml
courses/Python_Programming/lessons/Python-As-A-Calculator.yaml
courses/Python_Programming/lessons/Python-Control-Flow-Tools.yaml
courses/Python_Programming/lessons/Strings-In-Python.yaml
courses/Python_Programming/lessons/Tuples-Sets-and-Dictionaries.yaml
courses/Python_Programming/scripts/.DS_Store
courses/Python_Programming/scripts/__init__.py
swirlypy.egg-info/PKG-INFO
swirlypy.egg-info/SOURCES.txt
swirlypy.egg-info/dependency_links.txt
swirlypy.egg-info/requires.txt
swirlypy.egg-info/top_level.txt
