Metadata-Version: 1.1
Name: swirlypy
Version: 0.0.1
Summary: Python courseware
Home-page: https://github.com/Samarth2506/swirlypy
Author: Alexander Bauer/Samarth
Author-email: samarthmc@gmail.com
License: UNKNOWN
Download-URL: https://github.com/Samarth2506/swirlypy/archive/0.0.1.tar.gz
Platform: UNKNOWN
